aliyunsdkcr/__init__.py
aliyunsdkcr/endpoint.py
aliyunsdkcr/request/__init__.py
aliyunsdkcr/request/v20160607/CancelRepoBuildRequest.py
aliyunsdkcr/request/v20160607/CreateNamespaceRequest.py
aliyunsdkcr/request/v20160607/CreateRepoBuildRuleRequest.py
aliyunsdkcr/request/v20160607/CreateRepoRequest.py
aliyunsdkcr/request/v20160607/CreateRepoWebhookRequest.py
aliyunsdkcr/request/v20160607/CreateUserInfoRequest.py
aliyunsdkcr/request/v20160607/DeleteImageRequest.py
aliyunsdkcr/request/v20160607/DeleteNamespaceRequest.py
aliyunsdkcr/request/v20160607/DeleteRepoBuildRuleRequest.py
aliyunsdkcr/request/v20160607/DeleteRepoRequest.py
aliyunsdkcr/request/v20160607/DeleteRepoWebhookRequest.py
aliyunsdkcr/request/v20160607/GetAuthorizationTokenRequest.py
aliyunsdkcr/request/v20160607/GetImageLayerRequest.py
aliyunsdkcr/request/v20160607/GetImageManifestRequest.py
aliyunsdkcr/request/v20160607/GetNamespaceListRequest.py
aliyunsdkcr/request/v20160607/GetNamespaceRequest.py
aliyunsdkcr/request/v20160607/GetRegionListRequest.py
aliyunsdkcr/request/v20160607/GetRegionRequest.py
aliyunsdkcr/request/v20160607/GetRepoBuildListRequest.py
aliyunsdkcr/request/v20160607/GetRepoBuildRuleListRequest.py
aliyunsdkcr/request/v20160607/GetRepoBuildStatusRequest.py
aliyunsdkcr/request/v20160607/GetRepoListByNamespaceRequest.py
aliyunsdkcr/request/v20160607/GetRepoListRequest.py
aliyunsdkcr/request/v20160607/GetRepoRequest.py
aliyunsdkcr/request/v20160607/GetRepoTagRequest.py
aliyunsdkcr/request/v20160607/GetRepoTagScanListRequest.py
aliyunsdkcr/request/v20160607/GetRepoTagScanStatusRequest.py
aliyunsdkcr/request/v20160607/GetRepoTagScanSummaryRequest.py
aliyunsdkcr/request/v20160607/GetRepoTagsRequest.py
aliyunsdkcr/request/v20160607/GetRepoWebhookRequest.py
aliyunsdkcr/request/v20160607/StartImageScanRequest.py
aliyunsdkcr/request/v20160607/StartRepoBuildByRuleRequest.py
aliyunsdkcr/request/v20160607/UpdateNamespaceRequest.py
aliyunsdkcr/request/v20160607/UpdateRepoBuildRuleRequest.py
aliyun_python_sdk_cr-4.1.2.dist-info/LICENSE
aliyun_python_sdk_cr-4.1.2.dist-info/METADATA
aliyun_python_sdk_cr-4.1.2.dist-info/WHEEL
aliyun_python_sdk_cr-4.1.2.dist-info/top_level.txt
aliyun_python_sdk_cr-4.1.2.dist-info/RECORD
